openfc/__init__.py
openfc/db.py
openfc/bank/__init__.py
openfc/bond/__init__.py
openfc/bond/bond_history.py
openfc/bond/bond_info.py
openfc/commodities/__init__.py
openfc/commodities/commodities_gold.py
openfc/commodities/commondities_oil.py
openfc/digital_currency/__init__.py
openfc/emotion/__init__.py
openfc/fund/__init__.py
openfc/fund/fund_history.py
openfc/fund/fund_info.py
openfc/futures/__init__.py
openfc/fx/__init__.py
openfc/fx/fx_info.py
openfc/hmi/__init__.py
openfc/index/__init__.py
openfc/indicator/__init__.py
openfc/indicator/indicator_boll.py
openfc/indicator/indicator_cci.py
openfc/indicator/indicator_expma.py
openfc/indicator/indicator_kdj.py
openfc/indicator/indicator_ma.py
openfc/indicator/indicator_macd.py
openfc/indicator/indicator_rsi.py
openfc/macro/__init__.py
openfc/news/__init__.py
openfc/option/__init__.py
openfc/playback/__init__.py
openfc/report/__init__.py
openfc/stock/__init__.py
openfc/stock/stock_fundamentals.py
openfc/stock/stock_history.py
openfc/stock/stock_history_us.py
openfc/stock/stock_info.py
openfc/stock/stock_info_us.py
openfc/strategy/__init__.py
openfc/trade/__init__.py
openfc/utils/__init__.py
openfc-0.0.2.dist-info/LICENSE
openfc-0.0.2.dist-info/METADATA
openfc-0.0.2.dist-info/WHEEL
openfc-0.0.2.dist-info/top_level.txt
openfc-0.0.2.dist-info/RECORD
