Metadata-Version: 2.1
Name: openfc
Version: 0.0.2
Summary: An Open Financial Database
Author: Daniel Chen
Author-email: danielcxh@icloud.com
Classifier: Programming Language :: Python :: 3
Classifier: License :: OSI Approved :: MIT License
Classifier: Operating System :: OS Independent
License-File: LICENSE
Requires-Dist: pandas (==1.1.5)
Requires-Dist: requests (==2.22.0)
Requires-Dist: xlrd (>=1.2.0)
Requires-Dist: pyexcel-xls (==0.7.0)
Requires-Dist: yapf (==0.32.0)
Requires-Dist: beautifulsoup4 (==4.11.1)
Requires-Dist: mplfinance (==0.12.8b9)
Requires-Dist: py-mini-racer (==0.6.0)
